cloudsnorkel/cdk_turbo_layers/__init__.py
cloudsnorkel/cdk_turbo_layers/py.typed
cloudsnorkel/cdk_turbo_layers/_jsii/__init__.py
cloudsnorkel/cdk_turbo_layers/_jsii/cdk-turbo-layers@0.3.0.jsii.tgz
cloudsnorkel.cdk_turbo_layers-0.3.0.dist-info/LICENSE
cloudsnorkel.cdk_turbo_layers-0.3.0.dist-info/METADATA
cloudsnorkel.cdk_turbo_layers-0.3.0.dist-info/WHEEL
cloudsnorkel.cdk_turbo_layers-0.3.0.dist-info/top_level.txt
cloudsnorkel.cdk_turbo_layers-0.3.0.dist-info/RECORD
