Metadata-Version: 2.1
Name: cloudsnorkel.cdk-turbo-layers
Version: 0.3.0
Summary: Speed-up Lambda function deployment with dependency layers built in AWS
Home-page: https://github.com/CloudSnorkel/cdk-turbo-layers.git
Author: Amir Szekely<amir@cloudsnorkel.com>
License: Apache-2.0
Project-URL: Source, https://github.com/CloudSnorkel/cdk-turbo-layers.git
Classifier: Intended Audience :: Developers
Classifier: Operating System :: OS Independent
Classifier: Programming Language :: JavaScript
Classifier: Programming Language :: Python :: 3 :: Only
Classifier: Programming Language :: Python :: 3.8
Classifier: Programming Language :: Python :: 3.9
Classifier: Programming Language :: Python :: 3.10
Classifier: Programming Language :: Python :: 3.11
Classifier: Typing :: Typed
Classifier: Development Status :: 4 - Beta
Classifier: License :: OSI Approved
Requires-Python: ~=3.8
License-File: LICENSE
Requires-Dist: aws-cdk-lib<3.0.0,>=2.123.0
Requires-Dist: constructs<11.0.0,>=10.0.5
Requires-Dist: jsii<2.0.0,>=1.105.0
Requires-Dist: publication>=0.0.3
Requires-Dist: typeguard<4.3.0,>=2.13.3
